README.rst
setup.py
ppwd/__init__.py
ppwd/ppm.py
ppwd.egg-info/PKG-INFO
ppwd.egg-info/SOURCES.txt
ppwd.egg-info/dependency_links.txt
ppwd.egg-info/entry_points.txt
ppwd.egg-info/not-zip-safe
ppwd.egg-info/requires.txt
ppwd.egg-info/top_level.txt