Metadata-Version: 1.1
Name: ppwd
Version: 1.0
Summary: Private Password Manager
Home-page: https://github.com/fengyouchao/ppm
Author: Youchao Feng
Author-email: fengyouchao@gmail.com
License: Apache License, Version 2.0
Platform: UNKNOWN
Classifier: Development Status :: 3 - Alpha
Classifier: Environment :: Web Environment
Classifier: Intended Audience :: Developers
Classifier: Operating System :: OS Independent
Classifier: Programming Language :: Python
